block_scoping/__init__.py
block_scoping/check_files.py
block_scoping/scoped.py
block_scoping-0.2.3.dist-info/LICENSE
block_scoping-0.2.3.dist-info/METADATA
block_scoping-0.2.3.dist-info/WHEEL
block_scoping-0.2.3.dist-info/entry_points.txt
block_scoping-0.2.3.dist-info/top_level.txt
block_scoping-0.2.3.dist-info/RECORD
